capstone/32-bit-RISC-Processor/rtl/program_counter.sv
module program_counter (
    input  logic        clk,
    input  logic        reset,
    output logic [31:0] pc
);

always_ff @(posedge clk) begin
    if (reset)
        pc <= 32'b0;
    else
        pc <= pc + 32'd4;
end

endmodule

capstone/32-bit-RISC-Processor/verification/tb_program_counter.sv
`timescale 1ns/1ps

module tb_program_counter;

logic clk;
logic reset;
logic [31:0] pc;

program_counter uut (
    .clk(clk),
    .reset(reset),
    .pc(pc)
);

always #5 clk = ~clk;

initial begin
    $dumpfile("program_counter.vcd");
    $dumpvars(0, tb_program_counter);

    clk = 0;
    reset = 1;

    #10;
    reset = 0;

    #50;

    $finish;
end

initial begin
    $monitor("Time=%0t | reset=%b | PC=%h", $time, reset, pc);
end

endmodule

capstone/32-bit-RISC-Processor/waveforms/program_counter.vcd
$date
	Thu Sep 10 06:23:08 2026
$end
$version
	Icarus Verilog
$end
$timescale
	1ps
$end
$scope module tb_program_counter $end
$var wire 32 ! pc [31:0] $end
$var reg 1 " clk $end
$var reg 1 # reset $end
$scope module uut $end
$var wire 1 " clk $end
$var wire 1 # reset $end
$var reg 32 $ pc [31:0] $end
$upscope $end
$upscope $end
$enddefinitions $end
$comment Show the parameter values. $end
$dumpall
$end
#0
$dumpvars
bx $
1#
0"
bx !
$end
#5000
b0 !
b0 $
1"
#10000
0"
0#
#15000
b100 !
b100 $
1"
#20000
0"
#25000
b1000 !
b1000 $
1"
#30000
0"
#35000
b1100 !
b1100 $
1"
#40000
0"
#45000
b10000 !
b10000 $
1"
#50000
0"
#55000
b10100 !
b10100 $
1"
