capstone/32-bit-RISC-Processor/rtl/alu.sv
module alu (
    input  logic [31:0] a,
    input  logic [31:0] b,
    input  logic [3:0]  alu_control,

    output logic [31:0] result,
    output logic        zero
);

always_comb begin

    case (alu_control)

        4'b0000: result = a + b;       // ADD
        4'b0001: result = a - b;       // SUB
        4'b0010: result = a & b;       // AND
        4'b0011: result = a | b;       // OR
        4'b0100: result = a ^ b;       // XOR
        4'b0101: result = (a < b);     // LESS THAN

        default: result = 32'b0;

    endcase

end

assign zero = (result == 32'b0);

endmodule

capstone/32-bit-RISC-Processor/rtl/alu_decoder.sv
module alu_decoder (
    input  logic [1:0] alu_op,
    input  logic [5:0] funct,

    output logic [3:0] alu_control
);

always_comb begin

    case (alu_op)

        // Load / Store
        2'b00:
            alu_control = 4'b0000;   // ADD

        // Branch
        2'b01:
            alu_control = 4'b0001;   // SUB

        // R-type instructions
        2'b10: begin
            case (funct)

                6'b100000: alu_control = 4'b0000; // ADD
                6'b100010: alu_control = 4'b0001; // SUB
                6'b100100: alu_control = 4'b0010; // AND
                6'b100101: alu_control = 4'b0011; // OR
                6'b100110: alu_control = 4'b0100; // XOR

                default:   alu_control = 4'b0000;

            endcase
        end

        default:
            alu_control = 4'b0000;

    endcase

end

endmodule

capstone/32-bit-RISC-Processor/rtl/register_file.sv
module register_file (
    input  logic        clk,
    input  logic        reset,
    input  logic        write_enable,

    input  logic [4:0]  read_addr1,
    input  logic [4:0]  read_addr2,
    input  logic [4:0]  write_addr,

    input  logic [31:0] write_data,

    output logic [31:0] read_data1,
    output logic [31:0] read_data2
);

logic [31:0] registers [0:31];

integer i;

always_ff @(posedge clk) begin
    if (reset) begin
        for (i = 0; i < 32; i = i + 1)
            registers[i] <= 32'b0;
    end
    else if (write_enable && (write_addr != 5'd0)) begin
        registers[write_addr] <= write_data;
    end
end

always_comb begin
    if (read_addr1 == 5'd0)
        read_data1 = 32'b0;
    else
        read_data1 = registers[read_addr1];

    if (read_addr2 == 5'd0)
        read_data2 = 32'b0;
    else
        read_data2 = registers[read_addr2];
end

endmodule

capstone/32-bit-RISC-Processor/rtl/control_unit.sv
module control_unit (
    input  logic [5:0] opcode,

    output logic       reg_write,
    output logic       mem_to_reg,
    output logic       mem_write,
    output logic       alu_src,
    output logic       branch,
    output logic [1:0] alu_op
);

always_comb begin

    // Default values
    reg_write  = 1'b0;
    mem_to_reg = 1'b0;
    mem_write  = 1'b0;
    alu_src    = 1'b0;
    branch     = 1'b0;
    alu_op     = 2'b00;

    case (opcode)

        // R-type
        6'b000000: begin
            reg_write = 1'b1;
            alu_src   = 1'b0;
            alu_op    = 2'b10;
        end

        // LW
        6'b100011: begin
            reg_write  = 1'b1;
            mem_to_reg = 1'b1;
            alu_src    = 1'b1;
            alu_op     = 2'b00;
        end

        // SW
        6'b101011: begin
            mem_write = 1'b1;
            alu_src   = 1'b1;
            alu_op    = 2'b00;
        end

        // BEQ
        6'b000100: begin
            branch = 1'b1;
            alu_src = 1'b0;
            alu_op = 2'b01;
        end

        // ADDI
        6'b001000: begin
            reg_write = 1'b1;
            alu_src   = 1'b1;
            alu_op    = 2'b00;
        end

        default: begin
            // Keep default control signals
        end

    endcase

end

endmodule

capstone/32-bit-RISC-Processor/rtl/instruction_memory.sv
module instruction_memory (
    input  logic [31:0] address,
    output logic [31:0] instruction
);

logic [31:0] memory [0:15];

initial begin

    // ADDI R1, R0, 10
    memory[0] = 32'h2001000A;

    // ADDI R2, R0, 20
    memory[1] = 32'h20020014;

    // ADD R3, R1, R2
    memory[2] = 32'h00221820;

    memory[3]  = 32'h00000000;
    memory[4]  = 32'h00000000;
    memory[5]  = 32'h00000000;
    memory[6]  = 32'h00000000;
    memory[7]  = 32'h00000000;
    memory[8]  = 32'h00000000;
    memory[9]  = 32'h00000000;
    memory[10] = 32'h00000000;
    memory[11] = 32'h00000000;
    memory[12] = 32'h00000000;
    memory[13] = 32'h00000000;
    memory[14] = 32'h00000000;
    memory[15] = 32'h00000000;

end

always_comb begin
    instruction = memory[address[5:2]];
end

endmodule

capstone/32-bit-RISC-Processor/rtl/program_counter.sv
module program_counter (
    input  logic        clk,
    input  logic        reset,
    output logic [31:0] pc
);

always_ff @(posedge clk) begin
    if (reset)
        pc <= 32'b0;
    else
        pc <= pc + 32'd4;
end

endmodule

capstone/32-bit-RISC-Processor/rtl/risc_processor.sv
module risc_processor (
    input logic clk,
    input logic reset
);

    // Program Counter
    logic [31:0] pc;

    program_counter pc_unit (
        .clk(clk),
        .reset(reset),
        .pc(pc)
    );

    // Instruction Memory
    logic [31:0] instruction;

    instruction_memory imem (
        .address(pc),
        .instruction(instruction)
    );

    // Instruction fields
    logic [5:0] opcode;
    logic [4:0] rs;
    logic [4:0] rt;
    logic [4:0] rd;
    logic [5:0] funct;

    logic [15:0] immediate;
    logic [31:0] sign_extended_immediate;

    assign opcode = instruction[31:26];
    assign rs     = instruction[25:21];
    assign rt     = instruction[20:16];
    assign rd     = instruction[15:11];
    assign funct  = instruction[5:0];

    assign immediate = instruction[15:0];

    assign sign_extended_immediate =
        {{16{immediate[15]}}, immediate};

    // Control Unit
    logic       reg_write;
    logic       mem_to_reg;
    logic       mem_write;
    logic       alu_src;
    logic       branch;
    logic [1:0] alu_op;

    control_unit control (
        .opcode(opcode),
        .reg_write(reg_write),
        .mem_to_reg(mem_to_reg),
        .mem_write(mem_write),
        .alu_src(alu_src),
        .branch(branch),
        .alu_op(alu_op)
    );

    // Register File
    logic [31:0] read_data1;
    logic [31:0] read_data2;
    logic [31:0] write_data;

    logic [4:0] write_register;

    // R-type writes to RD
    // ADDI writes to RT
    assign write_register =
        (opcode == 6'b001000) ? rt : rd;

    register_file registers (
        .clk(clk),
        .reset(reset),
        .write_enable(reg_write),
        .read_addr1(rs),
        .read_addr2(rt),
        .write_addr(write_register),
        .write_data(write_data),
        .read_data1(read_data1),
        .read_data2(read_data2)
    );

    // ALU Decoder
    logic [3:0] alu_control;

    alu_decoder decoder (
        .alu_op(alu_op),
        .funct(funct),
        .alu_control(alu_control)
    );

    // ALU input selection
    logic [31:0] alu_input_b;
    logic [31:0] alu_result;
    logic        zero;

    assign alu_input_b =
        alu_src ? sign_extended_immediate : read_data2;

    alu alu_unit (
        .a(read_data1),
        .b(alu_input_b),
        .alu_control(alu_control),
        .result(alu_result),
        .zero(zero)
    );

    // Writeback
    assign write_data = alu_result;

endmodule

capstone/32-bit-RISC-Processor/verification/tb_risc_processor.sv
`timescale 1ns/1ps

module tb_risc_processor;

logic clk;
logic reset;

risc_processor uut (
    .clk(clk),
    .reset(reset)
);

always #5 clk = ~clk;

initial begin
    $dumpfile("risc_processor.vcd");
    $dumpvars(0, tb_risc_processor);

    clk = 0;
    reset = 1;

    // Reset processor
    #10;
    reset = 0;

    // Allow instructions to execute
    #40;

    // Verification checks
    if (uut.registers.registers[1] == 32'd10)
        $display("PASS: R1 = 10");
    else
        $display("FAIL: R1 = %0d", uut.registers.registers[1]);

    if (uut.registers.registers[2] == 32'd20)
        $display("PASS: R2 = 20");
    else
        $display("FAIL: R2 = %0d", uut.registers.registers[2]);

    if (uut.registers.registers[3] == 32'd30)
        $display("PASS: R3 = 30");
    else
        $display("FAIL: R3 = %0d", uut.registers.registers[3]);

    #10;
    $finish;
end

initial begin
    $monitor(
        "Time=%0t | PC=%h | Instruction=%h | ALU Result=%h",
        $time,
        uut.pc,
        uut.instruction,
        uut.alu_result
    );
end

endmodule

capstone/32-bit-RISC-Processor/waveforms/risc_processor.vcd
$date
	Thu Sep 10 07:23:09 2026
$end
$version
	Icarus Verilog
$end
$timescale
	1ps
$end
$scope module tb_risc_processor $end
$var reg 1 ! clk $end
$var reg 1 " reset $end
$scope module uut $end
$var wire 1 ! clk $end
$var wire 1 " reset $end
$var wire 32 # write_data [31:0] $end
$var wire 1 $ zero $end
$var wire 5 % write_register [4:0] $end
$var wire 32 & sign_extended_immediate [31:0] $end
$var wire 5 ' rt [4:0] $end
$var wire 5 ( rs [4:0] $end
$var wire 1 ) reg_write $end
$var wire 32 * read_data2 [31:0] $end
$var wire 32 + read_data1 [31:0] $end
$var wire 5 , rd [4:0] $end
$var wire 32 - pc [31:0] $end
$var wire 6 . opcode [5:0] $end
$var wire 1 / mem_write $end
$var wire 1 0 mem_to_reg $end
$var wire 32 1 instruction [31:0] $end
$var wire 16 2 immediate [15:0] $end
$var wire 6 3 funct [5:0] $end
$var wire 1 4 branch $end
$var wire 1 5 alu_src $end
$var wire 32 6 alu_result [31:0] $end
$var wire 2 7 alu_op [1:0] $end
$var wire 32 8 alu_input_b [31:0] $end
$var wire 4 9 alu_control [3:0] $end
$scope module alu_unit $end
$var wire 32 : b [31:0] $end
$var wire 1 $ zero $end
$var wire 4 ; alu_control [3:0] $end
$var wire 32 < a [31:0] $end
$var reg 32 = result [31:0] $end
$upscope $end
$scope module control $end
$var wire 6 > opcode [5:0] $end
$var reg 2 ? alu_op [1:0] $end
$var reg 1 5 alu_src $end
$var reg 1 4 branch $end
$var reg 1 0 mem_to_reg $end
$var reg 1 / mem_write $end
$var reg 1 ) reg_write $end
$upscope $end
$scope module decoder $end
$var wire 2 @ alu_op [1:0] $end
$var wire 6 A funct [5:0] $end
$var reg 4 B alu_control [3:0] $end
$upscope $end
$scope module imem $end
$var wire 32 C address [31:0] $end
$var reg 32 D instruction [31:0] $end
$upscope $end
$scope module pc_unit $end
$var wire 1 ! clk $end
$var wire 1 " reset $end
$var reg 32 E pc [31:0] $end
$upscope $end
$scope module registers $end
$var wire 1 ! clk $end
$var wire 5 F read_addr1 [4:0] $end
$var wire 5 G read_addr2 [4:0] $end
$var wire 1 " reset $end
$var wire 5 H write_addr [4:0] $end
$var wire 32 I write_data [31:0] $end
$var wire 1 ) write_enable $end
$var reg 32 J read_data1 [31:0] $end
$var reg 32 K read_data2 [31:0] $end
$var integer 32 L i [31:0] $end
$upscope $end
$upscope $end
$upscope $end
$enddefinitions $end
$comment Show the parameter values. $end
$dumpall
$end
#0
$dumpvars
bx L
bx K
bx J
bx I
bx H
bx G
bx F
bx E
bx D
bx C
b0 B
bx A
b0 @
b0 ?
bx >
bx =
bx <
b0 ;
bx :
b0 9
bx 8
b0 7
bx 6
05
04
bx 3
bx 2
bx 1
00
0/
bx .
bx -
bx ,
bx +
bx *
0)
bx (
bx '
bx &
bx %
x$
bx #
1"
0!
$end
#5000
0$
b1010 #
b1010 I
b1010 6
b1010 =
b1010 8
b1010 :
b0 *
b0 K
b0 +
b0 <
b0 J
b1 %
b1 H
15
1)
b1010 &
b1010 2
b1010 3
b1010 A
b0 ,
b1 '
b1 G
b0 (
b0 F
b1000 .
b1000 >
b100000000000010000000000001010 1
b100000000000010000000000001010 D
b0 -
b0 C
b0 E
b100000 L
1!
#10000
0!
0"
#15000
b10100 #
b10100 I
b10100 6
b10100 =
b10100 8
b10100 :
b10 %
b10 H
b10100 &
b10100 2
b10100 3
b10100 A
b10 '
b10 G
b0 *
b0 K
b100000000000100000000000010100 1
b100000000000100000000000010100 D
b100 -
b100 C
b100 E
1!
#20000
0!
#25000
b11110 #
b11110 I
b11110 6
b11110 =
b1010 +
b1010 <
b1010 J
b11 %
b11 H
b10 7
b10 ?
b10 @
05
1)
b1100000100000 &
b1100000100000 2
b100000 3
b100000 A
b11 ,
b1 (
b1 F
b0 .
b0 >
b1000100001100000100000 1
b1000100001100000100000 D
b10100 *
b10100 K
b1000 -
b1000 C
b1000 E
1!
#30000
0!
#35000
1$
b0 8
b0 :
b0 #
b0 I
b0 6
b0 =
b0 %
b0 H
b0 *
b0 K
b0 +
b0 <
b0 J
b0 &
b0 2
b0 3
b0 A
b0 ,
b0 '
b0 G
b0 (
b0 F
b0 1
b0 D
b1100 -
b1100 C
b1100 E
1!
#40000
0!
#45000
b10000 -
b10000 C
b10000 E
1!
#50000
0!
#55000
b10100 -
b10100 C
b10100 E
1!
