week-2/sequential-logic/rtl/d_flip_flop.v
module d_flip_flop (
    input logic clk,
    input logic reset,
    input logic d,
    output logic q
);

always_ff @(posedge clk) begin
    if (reset)
        q <= 1'b0;
    else
        q <= d;
end

endmodule

week-2/sequential-logic/verification/tb_d_flip_flop.v
`timescale 1ns/1ps

module tb_d_flip_flop;

logic clk;
logic reset;
logic d;
logic q;

d_flip_flop uut (
    .clk(clk),
    .reset(reset),
    .d(d),
    .q(q)
);

always #5 clk = ~clk;

initial begin
    $dumpfile("d_flip_flop.vcd");
    $dumpvars(0, tb_d_flip_flop);

    clk = 0;
    reset = 1;
    d = 0;

    #10;
    reset = 0;

    d = 1;
    #10;

    d = 0;
    #10;

    d = 1;
    #10;

    $finish;
end

endmodule

week-2/sequential-logic/waveforms/d_flip_flop.vcd
$date
	Thu Sep 10 15:59:32 2026
$end
$version
	Icarus Verilog
$end
$timescale
	1ps
$end
$scope module tb_d_flip_flop $end
$var wire 1 ! q $end
$var reg 1 " clk $end
$var reg 1 # d $end
$var reg 1 $ reset $end
$scope module uut $end
$var wire 1 " clk $end
$var wire 1 # d $end
$var wire 1 $ reset $end
$var reg 1 ! q $end
$upscope $end
$upscope $end
$enddefinitions $end
$comment Show the parameter values. $end
$dumpall
$end
#0
$dumpvars
1$
0#
0"
x!
$end
#5000
0!
1"
#10000
0"
1#
0$
#15000
1!
1"
#20000
0"
0#
#25000
0!
1"
#30000
0"
1#
#35000
1!
1"
