week-2/sequential-logic/rtl/johnson_counter.v
module johnson_counter (
    input logic clk,
    input logic reset,
    output logic [3:0] q
);

always_ff @(posedge clk) begin
    if (reset)
        q <= 4'b0000;
    else
        q <= {q[2:0], ~q[3]};
end

endmodule

week-2/sequential-logic/verification/tb_johnson_counter.v
`timescale 1ns/1ps

module tb_johnson_counter;

logic clk;
logic reset;
logic [3:0] q;

johnson_counter uut (
    .clk(clk),
    .reset(reset),
    .q(q)
);

always #5 clk = ~clk;

initial begin
    $dumpfile("johnson_counter.vcd");
    $dumpvars(0, tb_johnson_counter);

    clk = 0;
    reset = 1;

    #10;
    reset = 0;

    #80;

    $finish;
end

endmodule

week-2/sequential-logic/waveforms/johnson_counter.vcd
$date
	Thu Sep 10 16:51:17 2026
$end
$version
	Icarus Verilog
$end
$timescale
	1ps
$end
$scope module tb_johnson_counter $end
$var wire 4 ! q [3:0] $end
$var reg 1 " clk $end
$var reg 1 # reset $end
$scope module uut $end
$var wire 1 " clk $end
$var wire 1 # reset $end
$var reg 4 $ q [3:0] $end
$upscope $end
$upscope $end
$enddefinitions $end
$comment Show the parameter values. $end
$dumpall
$end
#0
$dumpvars
bx $
1#
0"
bx !
$end
#5000
b0 !
b0 $
1"
#10000
0"
0#
#15000
b1 !
b1 $
1"
#20000
0"
#25000
b11 !
b11 $
1"
#30000
0"
#35000
b111 !
b111 $
1"
#40000
0"
#45000
b1111 !
b1111 $
1"
#50000
0"
#55000
b1110 !
b1110 $
1"
#60000
0"
#65000
b1100 !
b1100 $
1"
#70000
0"
#75000
b1000 !
b1000 $
1"
#80000
0"
#85000
b0 !
b0 $
1"
