week-2/sequential-logic/rtl/parameterized_counter.v
module parameterized_counter #(
    parameter WIDTH = 8
) (
    input logic clk,
    input logic reset,
    output logic [WIDTH-1:0] q
);

always_ff @(posedge clk) begin
    if (reset)
        q <= '0;
    else
        q <= q + 1'b1;
end

endmodule

week-2/sequential-logic/verification/tb_parameterized_counter.v
`timescale 1ns/1ps

module tb_parameterized_counter;

logic clk;
logic reset;
logic [7:0] q;

parameterized_counter #(
    .WIDTH(8)
) uut (
    .clk(clk),
    .reset(reset),
    .q(q)
);

always #5 clk = ~clk;

initial begin
    $dumpfile("parameterized_counter_8bit.vcd");
    $dumpvars(0, tb_parameterized_counter);

    clk = 0;
    reset = 1;

    #10;
    reset = 0;

    #160;

    $finish;
end

endmodule

week-2/sequential-logic/waveforms/parameterized_counter_8bit.vcd
$date
	Thu Sep 10 17:36:02 2026
$end
$version
	Icarus Verilog
$end
$timescale
	1ps
$end
$scope module tb_parameterized_counter $end
$var wire 8 ! q [7:0] $end
$var reg 1 " clk $end
$var reg 1 # reset $end
$scope module uut $end
$var wire 1 " clk $end
$var wire 1 # reset $end
$var parameter 32 $ WIDTH $end
$var reg 8 % q [7:0] $end
$upscope $end
$upscope $end
$enddefinitions $end
$comment Show the parameter values. $end
$dumpall
b1000 $
$end
#0
$dumpvars
bx %
1#
0"
bx !
$end
#5000
b0 !
b0 %
1"
#10000
0"
0#
#15000
b1 !
b1 %
1"
#20000
0"
#25000
b10 !
b10 %
1"
#30000
0"
#35000
b11 !
b11 %
1"
#40000
0"
#45000
b100 !
b100 %
1"
#50000
0"
#55000
b101 !
b101 %
1"
#60000
0"
#65000
b110 !
b110 %
1"
#70000
0"
#75000
b111 !
b111 %
1"
#80000
0"
#85000
b1000 !
b1000 %
1"
#90000
0"
#95000
b1001 !
b1001 %
1"
#100000
0"
#105000
b1010 !
b1010 %
1"
#110000
0"
#115000
b1011 !
b1011 %
1"
#120000
0"
#125000
b1100 !
b1100 %
1"
#130000
0"
#135000
b1101 !
b1101 %
1"
#140000
0"
#145000
b1110 !
b1110 %
1"
#150000
0"
#155000
b1111 !
b1111 %
1"
#160000
0"
#165000
b10000 !
b10000 %
1"
