week-2/sequential-logic/rtl/parameterized_shift_register.v
module parameterized_shift_register #(
    parameter WIDTH = 8
) (
    input logic clk,
    input logic reset,
    input logic serial_in,
    output logic [WIDTH-1:0] q
);

always_ff @(posedge clk) begin
    if (reset)
        q <= '0;
    else
        q <= {q[WIDTH-2:0], serial_in};
end

endmodule

week-2/sequential-logic/verification/tb_parameterized_shift_register.v
`timescale 1ns/1ps

module tb_parameterized_shift_register;

logic clk;
logic reset;
logic serial_in;
logic [3:0] q;

parameterized_shift_register #(
    .WIDTH(4)
) uut (
    .clk(clk),
    .reset(reset),
    .serial_in(serial_in),
    .q(q)
);

always #5 clk = ~clk;

initial begin
    $dumpfile("parameterized_shift_register_4bit.vcd");
    $dumpvars(0, tb_parameterized_shift_register);

    clk = 0;
    reset = 1;
    serial_in = 0;

    #10;
    reset = 0;

    serial_in = 1;
    #10;

    serial_in = 0;
    #10;

    serial_in = 1;
    #10;

    serial_in = 1;
    #10;

    serial_in = 0;
    #10;

    serial_in = 1;
    #10;

    $finish;
end

endmodule

week-2/sequential-logic/waveforms/parameterized_shift_register_4bit.vcd
$date
	Thu Sep 10 17:48:48 2026
$end
$version
	Icarus Verilog
$end
$timescale
	1ps
$end
$scope module tb_parameterized_shift_register $end
$var wire 4 ! q [3:0] $end
$var reg 1 " clk $end
$var reg 1 # reset $end
$var reg 1 $ serial_in $end
$scope module uut $end
$var wire 1 " clk $end
$var wire 1 # reset $end
$var wire 1 $ serial_in $end
$var parameter 32 % WIDTH $end
$var reg 4 & q [3:0] $end
$upscope $end
$upscope $end
$enddefinitions $end
$comment Show the parameter values. $end
$dumpall
b100 %
$end
#0
$dumpvars
bx &
0$
1#
0"
bx !
$end
#5000
b0 !
b0 &
1"
#10000
0"
1$
0#
#15000
b1 !
b1 &
1"
#20000
0"
0$
#25000
b10 !
b10 &
1"
#30000
0"
1$
#35000
b101 !
b101 &
1"
#40000
0"
#45000
b1011 !
b1011 &
1"
#50000
0"
0$
#55000
b110 !
b110 &
1"
#60000
0"
1$
#65000
b1101 !
b1101 &
1"
