week-2/sequential-logic/rtl/register_8bit.v
module register_8bit (
    input logic clk,
    input logic reset,
    input logic [7:0] d,
    output logic [7:0] q
);

always_ff @(posedge clk) begin
    if (reset)
        q <= 8'b0;
    else
        q <= d;
end

endmodule

week-2/sequential-logic/verification/tb_register_8bit.v
`timescale 1ns/1ps

module tb_register_8bit;

logic clk;
logic reset;
logic [7:0] d;
logic [7:0] q;

register_8bit uut (
    .clk(clk),
    .reset(reset),
    .d(d),
    .q(q)
);

always #5 clk = ~clk;

initial begin
    $dumpfile("register_8bit.vcd");
    $dumpvars(0, tb_register_8bit);

    clk = 0;
    reset = 1;
    d = 8'b00000000;

    #10;
    reset = 0;

    d = 8'b10101010;
    #10;

    d = 8'b11110000;
    #10;

    d = 8'b01010101;
    #10;

    d = 8'b11001100;
    #10;

    $finish;
end

endmodule

week-2/sequential-logic/waveforms/register_8bit.vcd
$date
	Thu Sep 10 16:13:18 2026
$end
$version
	Icarus Verilog
$end
$timescale
	1ps
$end
$scope module tb_register_8bit $end
$var wire 8 ! q [7:0] $end
$var reg 1 " clk $end
$var reg 8 # d [7:0] $end
$var reg 1 $ reset $end
$scope module uut $end
$var wire 1 " clk $end
$var wire 8 % d [7:0] $end
$var wire 1 $ reset $end
$var reg 8 & q [7:0] $end
$upscope $end
$upscope $end
$enddefinitions $end
$comment Show the parameter values. $end
$dumpall
$end
#0
$dumpvars
bx &
b0 %
1$
b0 #
0"
bx !
$end
#5000
b0 !
b0 &
1"
#10000
0"
b10101010 #
b10101010 %
0$
#15000
b10101010 !
b10101010 &
1"
#20000
0"
b11110000 #
b11110000 %
#25000
b11110000 !
b11110000 &
1"
#30000
0"
b1010101 #
b1010101 %
#35000
b1010101 !
b1010101 &
1"
#40000
0"
b11001100 #
b11001100 %
#45000
b11001100 !
b11001100 &
1"
