week-2/sequential-logic/rtl/shift_register.v
module shift_register (
    input logic clk,
    input logic reset,
    input logic serial_in,
    output logic [7:0] q
);

always_ff @(posedge clk) begin
    if (reset)
        q <= 8'b0;
    else
        q <= {q[6:0], serial_in};
end

endmodule

week-2/sequential-logic/verification/tb_shift_register.v
`timescale 1ns/1ps

module tb_shift_register;

logic clk;
logic reset;
logic serial_in;
logic [7:0] q;

shift_register uut (
    .clk(clk),
    .reset(reset),
    .serial_in(serial_in),
    .q(q)
);

always #5 clk = ~clk;

initial begin
    $dumpfile("shift_register.vcd");
    $dumpvars(0, tb_shift_register);

    clk = 0;
    reset = 1;
    serial_in = 0;

    #10;
    reset = 0;

    serial_in = 1;
    #10;

    serial_in = 0;
    #10;

    serial_in = 1;
    #10;

    serial_in = 1;
    #10;

    serial_in = 0;
    #10;

    $finish;
end

endmodule

week-2/sequential-logic/waveforms/shift_register.vcd
$date
	Thu Sep 10 16:22:00 2026
$end
$version
	Icarus Verilog
$end
$timescale
	1ps
$end
$scope module tb_shift_register $end
$var wire 8 ! q [7:0] $end
$var reg 1 " clk $end
$var reg 1 # reset $end
$var reg 1 $ serial_in $end
$scope module uut $end
$var wire 1 " clk $end
$var wire 1 # reset $end
$var wire 1 $ serial_in $end
$var reg 8 % q [7:0] $end
$upscope $end
$upscope $end
$enddefinitions $end
$comment Show the parameter values. $end
$dumpall
$end
#0
$dumpvars
bx %
0$
1#
0"
bx !
$end
#5000
b0 !
b0 %
1"
#10000
0"
1$
0#
#15000
b1 !
b1 %
1"
#20000
0"
0$
#25000
b10 !
b10 %
1"
#30000
0"
1$
#35000
b101 !
b101 %
1"
#40000
0"
#45000
b1011 !
b1011 %
1"
#50000
0"
0$
#55000
b10110 !
b10110 %
1"
