week-2/sequential-logic/rtl/up_counter_4bit.v
module up_counter_4bit (
    input logic clk,
    input logic reset,
    output logic [3:0] q
);

always_ff @(posedge clk) begin
    if (reset)
        q <= 4'b0000;
    else
        q <= q + 1'b1;
end

endmodule

week-2/sequential-logic/verification/tb_up_counter_4bit.v
`timescale 1ns/1ps

module tb_up_counter_4bit;

logic clk;
logic reset;
logic [3:0] q;

up_counter_4bit uut (
    .clk(clk),
    .reset(reset),
    .q(q)
);

always #5 clk = ~clk;

initial begin
    $dumpfile("up_counter_4bit.vcd");
    $dumpvars(0, tb_up_counter_4bit);

    clk = 0;
    reset = 1;

    #10;
    reset = 0;

    #160;

    $finish;
end

endmodule

week-2/sequential-logic/waveforms/up_counter_4bit.vcd
$date
	Thu Sep 10 16:27:41 2026
$end
$version
	Icarus Verilog
$end
$timescale
	1ps
$end
$scope module tb_up_counter_4bit $end
$var wire 4 ! q [3:0] $end
$var reg 1 " clk $end
$var reg 1 # reset $end
$scope module uut $end
$var wire 1 " clk $end
$var wire 1 # reset $end
$var reg 4 $ q [3:0] $end
$upscope $end
$upscope $end
$enddefinitions $end
$comment Show the parameter values. $end
$dumpall
$end
#0
$dumpvars
bx $
1#
0"
bx !
$end
#5000
b0 !
b0 $
1"
#10000
0"
0#
#15000
b1 !
b1 $
1"
#20000
0"
#25000
b10 !
b10 $
1"
#30000
0"
#35000
b11 !
b11 $
1"
#40000
0"
#45000
b100 !
b100 $
1"
#50000
0"
#55000
b101 !
b101 $
1"
#60000
0"
#65000
b110 !
b110 $
1"
#70000
0"
#75000
b111 !
b111 $
1"
#80000
0"
#85000
b1000 !
b1000 $
1"
#90000
0"
#95000
b1001 !
b1001 $
1"
#100000
0"
#105000
b1010 !
b1010 $
1"
#110000
0"
#115000
b1011 !
b1011 $
1"
#120000
0"
#125000
b1100 !
b1100 $
1"
#130000
0"
#135000
b1101 !
b1101 $
1"
#140000
0"
#145000
b1110 !
b1110 $
1"
#150000
0"
#155000
b1111 !
b1111 $
1"
#160000
0"
#165000
b0 !
b0 $
1"
