week-1/verilog-basics/rtl/full_adder.v
module full_adder (
    input  wire a,
    input  wire b,
    input  wire cin,
    output wire sum,
    output wire carry
);

assign sum   = a ^ b ^ cin;
assign carry = (a & b) | (b & cin) | (a & cin);

endmodule

week-1/mini-project/digital-arithmetic-logic-circuit-library/verification/tb_full_adder.v
`timescale 1ns/1ps

module tb_full_adder;

reg a;
reg b;
reg cin;
wire sum;
wire carry;

full_adder uut (
    .a(a),
    .b(b),
    .cin(cin),
    .sum(sum),
    .carry(carry)
);

initial begin
    $dumpfile("full_adder.vcd");
    $dumpvars(0, tb_full_adder);

    $monitor("Time=%0t | a=%b b=%b cin=%b | sum=%b carry=%b",
             $time, a, b, cin, sum, carry);

    a = 0; b = 0; cin = 0;
    #10;

    a = 0; b = 0; cin = 1;
    #10;

    a = 0; b = 1; cin = 0;
    #10;

    a = 0; b = 1; cin = 1;
    #10;

    a = 1; b = 0; cin = 0;
    #10;

    a = 1; b = 0; cin = 1;
    #10;

    a = 1; b = 1; cin = 0;
    #10;

    a = 1; b = 1; cin = 1;
    #10;

    $finish;
end

endmodule

week-1/documentation/waveforms/full_adder.vcd
$date
	Thu Sep 10 05:08:17 2026
$end
$version
	Icarus Verilog
$end
$timescale
	1ps
$end
$scope module tb_full_adder $end
$var wire 1 ! sum $end
$var wire 1 " carry $end
$var reg 1 # a $end
$var reg 1 $ b $end
$var reg 1 % cin $end
$scope module uut $end
$var wire 1 # a $end
$var wire 1 $ b $end
$var wire 1 " carry $end
$var wire 1 % cin $end
$var wire 1 ! sum $end
$upscope $end
$upscope $end
$enddefinitions $end
$comment Show the parameter values. $end
$dumpall
$end
#0
$dumpvars
0%
0$
0#
0"
0!
$end
#10000
1!
1%
#20000
0%
1$
#30000
1"
0!
1%
#40000
0"
1!
0%
0$
1#
#50000
1"
0!
1%
#60000
0%
1$
#70000
1!
1%
